bodyguard/__init__.py
bodyguard/exceptions.py
bodyguard/tools.py
bodyguard0-0.0.7.dist-info/LICENSE
bodyguard0-0.0.7.dist-info/METADATA
bodyguard0-0.0.7.dist-info/WHEEL
bodyguard0-0.0.7.dist-info/top_level.txt
bodyguard0-0.0.7.dist-info/RECORD
