Metadata-Version: 2.1
Name: bodyguard0
Version: 0.0.7
Summary: Heavy machinery for Python (tools, utilities, etc)
Home-page: https://github.com/muhlbach/bodyguard
Author: Nicolaj Søndergaard Mühlbach
Author-email: n.muhlbach@gmail.com
License: MIT License
Keywords: utilities,tools
Platform: UNKNOWN
Classifier: Programming Language :: Python :: 3
Classifier: License :: OSI Approved :: MIT License
Classifier: Operating System :: OS Independent
Requires-Python: >=3.6
License-File: LICENSE
